emailcrawl1/__init__.py
emailcrawl1/emailcrawl1.py
emailcrawl1-0.0.3.dist-info/METADATA
emailcrawl1-0.0.3.dist-info/WHEEL
emailcrawl1-0.0.3.dist-info/RECORD
